CHANGELOG.md
README.md
plugintoolbox/__init__.py
plugintoolbox/agent_operations.py
plugintoolbox/brute_force_credentials_generator.py
plugintoolbox/brute_force_credentials_provider.py
plugintoolbox/brute_force_exploiter.py
plugintoolbox/dropper_script_wrapper_template.py
plugintoolbox/file_filters.py
plugintoolbox/http_bytes_server.py
plugintoolbox/i_remote_access_client.py
plugintoolbox/i_remote_access_client_factory.py
plugintoolbox/py.typed
plugintoolbox/web_tools.py
monkey_plugintoolbox-0.4.0.dist-info/LICENSE
monkey_plugintoolbox-0.4.0.dist-info/METADATA
monkey_plugintoolbox-0.4.0.dist-info/WHEEL
monkey_plugintoolbox-0.4.0.dist-info/RECORD
